assembly_ai/__init__.py
assembly_ai/example.py
aai_demo-0.0.1.dist-info/LICENSE
aai_demo-0.0.1.dist-info/METADATA
aai_demo-0.0.1.dist-info/WHEEL
aai_demo-0.0.1.dist-info/top_level.txt
aai_demo-0.0.1.dist-info/RECORD
